google_datacatalog_mysql_connector-0.10.0-py3.8-nspkg.pth
google/datacatalog_connectors/mysql_/__init__.py
google/datacatalog_connectors/mysql_/datacatalog_cli.py
google/datacatalog_connectors/mysql_/config/__init__.py
google/datacatalog_connectors/mysql_/config/metadata_definition.json
google/datacatalog_connectors/mysql_/config/metadata_query.sql
google/datacatalog_connectors/mysql_/config/num_rows_query.sql
google/datacatalog_connectors/mysql_/scrape/__init__.py
google/datacatalog_connectors/mysql_/scrape/metadata_scraper.py
google/datacatalog_connectors/mysql_/scrape/query_assembler.py
google_datacatalog_mysql_connector-0.10.0.dist-info/METADATA
google_datacatalog_mysql_connector-0.10.0.dist-info/WHEEL
google_datacatalog_mysql_connector-0.10.0.dist-info/entry_points.txt
google_datacatalog_mysql_connector-0.10.0.dist-info/namespace_packages.txt
google_datacatalog_mysql_connector-0.10.0.dist-info/top_level.txt
google_datacatalog_mysql_connector-0.10.0.dist-info/RECORD
